rxnsmiles2rinchi/__init__.py
rxnsmiles2rinchi/rinchi.py
rxnsmiles2rinchi/bin/.DS_Store
rxnsmiles2rinchi/bin/rinchi_lib/.DS_Store
rxnsmiles2rinchi/bin/rinchi_lib/linux/armv6l/librinchi.so.1.0.0
rxnsmiles2rinchi/bin/rinchi_lib/linux/x86/librinchi.so.1.0.0
rxnsmiles2rinchi/bin/rinchi_lib/linux/x86_64/librinchi.so.1.0.0
rxnsmiles2rinchi/bin/rinchi_lib/mac/.DS_Store
rxnsmiles2rinchi/bin/rinchi_lib/mac/arm64/librinchi.dylib.1.0.0
rxnsmiles2rinchi/bin/rinchi_lib/windows/x86/librinchi.dll
rxnsmiles2rinchi/bin/rinchi_lib/windows/x86_64/librinchi.dll
rxnsmiles2rinchi-0.1.1.dist-info/METADATA
rxnsmiles2rinchi-0.1.1.dist-info/WHEEL
rxnsmiles2rinchi-0.1.1.dist-info/top_level.txt
rxnsmiles2rinchi-0.1.1.dist-info/RECORD
