Metadata-Version: 2.4
Name: rxnsmiles2rinchi
Version: 0.1.1
Summary: Python wrapper for the IUPAC RInChI library
Author-email: Your Name <your@email.com>
License: IUPAC/InChI Trust License No.1.0
Classifier: Programming Language :: Python :: 3
Classifier: Operating System :: OS Independent
Requires-Python: >=3.8
Requires-Dist: rdkit
